{
    "sources": {
        "bitbake": {
            "git-remote": {
                "branch": "2.18",
                "rev": "a2dd9be788274d9c7280be5b1be5eb5c3990cf54",
                "uri": "https://git.openembedded.org/bitbake"
            }
        },
        "meta-yocto": {
            "git-remote": {
                "branch": "wrynose",
                "rev": "904846ae078ee20de073040ebb77c86e19250f56",
                "uri": "https://git.yoctoproject.org/meta-yocto"
            }
        },
        "openembedded-core": {
            "git-remote": {
                "branch": "wrynose",
                "rev": "080e184ad9a07b469da7e8b045a93cefd5bf2438",
                "uri": "https://git.openembedded.org/openembedded-core"
            }
        },
        "yocto-docs": {
            "git-remote": {
                "branch": "wrynose",
                "rev": "6b78593bed7174245fd7f6861263c69a3c439a74",
                "uri": "https://git.yoctoproject.org/yocto-docs"
            }
        }
    }
}